acelectricity.py
ac_electricity-0.4.7.dist-info/LICENSE
ac_electricity-0.4.7.dist-info/METADATA
ac_electricity-0.4.7.dist-info/WHEEL
ac_electricity-0.4.7.dist-info/top_level.txt
ac_electricity-0.4.7.dist-info/RECORD
