Metadata-Version: 2.1
Name: ac-electricity
Version: 0.4.7
Summary: An educational module about linear AC electrical circuits
Home-page: https://framagit.org/fsincere/ac-electricity
Author: Fabrice Sincère
Author-email: fabrice.sincere@ac-grenoble.fr
Maintainer: Fabrice Sincère
Maintainer-email: fabrice.sincere@ac-grenoble.fr
Classifier: Programming Language :: Python :: 3
Classifier: Intended Audience :: Education
Classifier: Intended Audience :: Science/Research
Classifier: Topic :: Scientific/Engineering :: Physics
Classifier: License :: OSI Approved :: GNU General Public License v3 (GPLv3)
Classifier: Operating System :: OS Independent
Requires-Python: >=3
License-File: LICENSE
Requires-Dist: matplotlib
